README.md
setup.py
dataswissknife/__init__.py
dataswissknife/classification_modelling.py
dataswissknife/clean_data.py
dataswissknife/cli_tool.py
dataswissknife/load_data.py
dataswissknife/log_tracker.py
dataswissknife/main_code.py
dataswissknife/preprocess_data.py
dataswissknife/visualize_data.py
dataswissknife.egg-info/PKG-INFO
dataswissknife.egg-info/SOURCES.txt
dataswissknife.egg-info/dependency_links.txt
dataswissknife.egg-info/entry_points.txt
dataswissknife.egg-info/requires.txt
dataswissknife.egg-info/top_level.txt