Metadata-Version: 2.1
Name: dataswissknife
Version: 0.1a4
Summary: A Handy Little Tool to aid your Data Science Projects
Home-page: https://github.com/ry05/dataswissknife
Author: Ramshankar Yadhunath
Author-email: yadramshankar@gmail.com
License: UNKNOWN
Platform: UNKNOWN
Classifier: Development Status :: 3 - Alpha
Classifier: Intended Audience :: Education
Classifier: Intended Audience :: Science/Research
Classifier: Programming Language :: Python :: 3
Classifier: License :: OSI Approved :: MIT License
Classifier: Operating System :: OS Independent
Classifier: Natural Language :: English
Classifier: Topic :: Education
Classifier: Topic :: Scientific/Engineering
Requires-Python: >=3.7
